{ 
	"39" : {"G" : 10},
	"40" : {"T" : 3425},
	"41" : {"G" : 3448},
	"42" : {"P" : 3454},
	"43" : {"G" : 3421},
	"44" : {"S" : 3400, "T" : 50},
	"45" : {"N" : 3454},
	"46" : {"V" : 3473},
	"47" : {"S" : 3474},
	"48" : {"T" : 3474},
	"49" : {"V" : 3478},
	"50" : {"Q" : 3477},
	"51" : {"C" : 3397},
	"52" : {"T" : 3482},
	"53" : {"H" : 3467},
	"54" : {"A" : 1, "G" : 3419, "R" : 2, "T" : 40},
	"55" : {"I" : 3409},
	"56" : {"H" : 29, "R" : 3418},
	"57" : {"P" : 3471},
	"58" : {"L" : 3, "Q" : 45, "V" : 3405},
	"59" : {"E" : 37, "V" : 3399},
	"60" : {"A" : 1, "G" : 55, "S" : 3392},
	"61" : {"T" : 3465},
	"62" : {"Q" : 3408},
	"63" : {"K" : 57, "L" : 3357},
	"64" : {"L" : 3384},
	"65" : {"F" : 2592, "L" : 666},
	"66" : {"N" : 3418},
	"67" : {"G" : 3404},
	"68" : {"S" : 3392},
	"69" : {"L" : 3406},
	"70" : {"A" : 2873, "S" : 518},
	"71" : {"E" : 3396},
	"72" : {"E" : 3220, "K" : 141},
	"73" : {"E" : 637, "G" : 2522},
	"74" : {"A" : 232, "V" : 3130},
	"75" : {"V" : 3400},
	"76" : {"I" : 3401},
	"77" : {"R" : 3392},
	"78" : {"S" : 3394},
	"79" : {"E" : 3362},
	"80" : {"N" : 3393},
	"81" : {"F" : 736, "L" : 2635},
	"82" : {"K" : 1403, "T" : 648},
	"83" : {"D" : 2744, "N" : 640},
	"84" : {"N" : 3289, "S" : 98},
	"85" : {"A" : 3389},
	"86" : {"K" : 3355},
	"87" : {"I" : 36, "T" : 3322},
	"88" : {"I" : 3353},
	"89" : {"L" : 3374},
	"90" : {"V" : 3375},
	"91" : {"Q" : 3371},
	"92" : {"L" : 3376},
	"93" : {"N" : 3349},
	"94" : {"E" : 3338, "N" : 1},
	"95" : {"S" : 3344},
	"96" : {"V" : 3344},
	"97" : {"V" : 3368},
	"98" : {"I" : 3365},
	"99" : {"N" : 3369},
	"100" : {"C" : 3358},
	"101" : {"T" : 3340},
	"102" : {"R" : 3335},
	"103" : {"L" : 2793, "P" : 541},
	"104" : {"N" : 2810},
	"105" : {"N" : 2822},
	"106" : {"N" : 2814},
	"107" : {"T" : 3329},
	"108" : {"R" : 2793, "T" : 508},
	"109" : {"K" : 3328},
	"110" : {"H" : 2, "N" : 1, "Q" : 511, "R" : 48, "S" : 2550},
	"111" : {"I" : 3329},
	"112" : {"P" : 107, "R" : 513, "T" : 2651},
	"113" : {"I" : 3288},
	"114" : {"K" : 1, "M" : 10, "S" : 498},
	"115" : {"G" : 2, "H" : 8, "Q" : 2, "R" : 6, "Y" : 498},
	"116" : {"G" : 3342, "P" : 2},
	"117" : {"G" : 2, "P" : 3347},
	"118" : {"G" : 3346, "R" : 2},
	"119" : {"A" : 2, "K" : 2679, "R" : 622},
	"120" : {"A" : 3316},
	"121" : {"F" : 2797, "I" : 4, "N" : 28, "V" : 2, "Y" : 4},
	"122" : {"C" : 1, "G" : 8, "M" : 30, "S" : 1, "T" : 2, "V" : 539, "W" : 97, "Y" : 2601},
	"123" : {"A" : 26, "G" : 2647, "S" : 28, "T" : 641},
	"124" : {"D" : 2, "T" : 3310},
	"125" : {"D" : 3160, "E" : 6, "K" : 2},
	"126" : {"I" : 2655, "K" : 515, "L" : 2, "N" : 1, "Y" : 116},
	"127" : {"G" : 4, "I" : 2831},
	"128" : {"E" : 2, "G" : 3343, "N" : 2},
	"129" : {"D" : 1, "E" : 512, "I" : 2, "M" : 2, "N" : 2827},
	"130" : {"I" : 2826, "K" : 2, "M" : 522, "R" : 2},
	"131" : {"K" : 518, "Q" : 4, "R" : 2845},
	"132" : {"A" : 4, "Q" : 3344},
	"133" : {"A" : 3348, "H" : 4},
	"134" : {"C" : 4, "H" : 3342},
	"135" : {"C" : 3338, "N" : 4},
	"136" : {"L" : 4, "N" : 3342},
	"137" : {"L" : 3338, "T" : 4},
	"138" : {"R" : 4, "S" : 7, "T" : 3329},
	"139" : {"A" : 4, "R" : 3339},
	"140" : {"A" : 3375, "K" : 4},
	"141" : {"K" : 3237, "S" : 33, "T" : 78, "W" : 4},
	"142" : {"N" : 4, "W" : 3371},
	"143" : {"D" : 17, "N" : 3328, "S" : 2},
	"144" : {"N" : 2806, "P" : 31, "S" : 525, "T" : 4},
	"145" : {"A" : 92, "I" : 3, "L" : 34, "P" : 4, "T" : 3236},
	"146" : {"G" : 2, "L" : 3367, "R" : 2},
	"147" : {"E" : 2, "G" : 433, "K" : 98, "L" : 4, "R" : 2830},
	"148" : {"I" : 2, "L" : 3230, "M" : 43, "R" : 4, "V" : 2, "W" : 74},
	"149" : {"A" : 4, "I" : 2763, "V" : 605},
	"150" : {"A" : 3374, "S" : 2, "T" : 2},
	"151" : {"K" : 4, "S" : 599, "T" : 2719},
	"152" : {"K" : 3358, "L" : 4},
	"153" : {"L" : 3374, "Q" : 4},
	"154" : {"E" : 4, "Q" : 3356},
	"155" : {"E" : 3337, "Q" : 4},
	"156" : {"F" : 4, "Q" : 3209},
	"157" : {"F" : 3340},
	"158" : {"E" : 69, "G" : 12, "K" : 13},
	"159" : {"E" : 2477, "K" : 651, "N" : 85},
	"160" : {"K" : 4, "N" : 3275},
	"161" : {"K" : 3267, "T" : 4},
	"162" : {"I" : 4, "T" : 3294},
	"163" : {"I" : 3012, "V" : 4},
	"164" : {"F" : 4, "V" : 3315},
	"165" : {"F" : 3265, "N" : 4},
	"166" : {"K" : 459, "N" : 2734, "Q" : 4},
	"167" : {"Q" : 3340, "S" : 4},
	"168" : {"S" : 3359},
	"169" : {"G" : 4, "S" : 3352},
	"170" : {"G" : 3275},
	"171" : {"D" : 4, "G" : 3269},
	"172" : {"D" : 3255, "P" : 4},
	"173" : {"E" : 4, "P" : 3321},
	"174" : {"A" : 4, "E" : 3322},
	"175" : {"A" : 3274, "L" : 4},
	"176" : {"A" : 31, "L" : 3190, "T" : 4},
	"177" : {"T" : 3250},
	"179" : {"S" : 24},
	"180" : {"F" : 24},
	"181" : {"N" : 24},
	"190" : {"N" : 12},
	"191" : {"S" : 12},
	"192" : {"T" : 12},
	"193" : {"I" : 12},
	"194" : {"L" : 12},
	"195" : {"F" : 12},
	"197" : {"S" : 12},
	"200" : {"I" : 12},
	"203" : {"K" : 10},
	"205" : {"S" : 12},
	"207" : {"E" : 11},
	"208" : {"C" : 11}
}
