{ 
	"54" : {"N" : 4136},
	"55" : {"P" : 4161},
	"56" : {"Y" : 4168},
	"57" : {"N" : 4174},
	"58" : {"T" : 4180},
	"59" : {"P" : 4208},
	"60" : {"V" : 4208},
	"61" : {"F" : 4182},
	"62" : {"A" : 4211},
	"63" : {"I" : 3920},
	"64" : {"K" : 3922},
	"65" : {"K" : 2896},
	"66" : {"K" : 4121},
	"67" : {"D" : 4167},
	"68" : {"S" : 4223},
	"69" : {"T" : 4223},
	"70" : {"K" : 4220},
	"71" : {"W" : 4216},
	"72" : {"R" : 4179},
	"73" : {"K" : 4216},
	"74" : {"L" : 4225},
	"75" : {"V" : 4229},
	"76" : {"D" : 4229},
	"77" : {"F" : 4225},
	"78" : {"R" : 4229},
	"79" : {"E" : 4230},
	"80" : {"L" : 4232},
	"81" : {"N" : 4231},
	"82" : {"K" : 4232},
	"83" : {"R" : 4232},
	"84" : {"T" : 4235},
	"85" : {"Q" : 4235},
	"86" : {"D" : 4218},
	"87" : {"F" : 4219},
	"88" : {"W" : 4215},
	"89" : {"E" : 4238},
	"90" : {"V" : 4239},
	"91" : {"Q" : 4241},
	"92" : {"L" : 4241},
	"93" : {"G" : 4242},
	"94" : {"I" : 4243},
	"95" : {"P" : 4235},
	"96" : {"H" : 4237},
	"97" : {"P" : 4245},
	"98" : {"A" : 4244},
	"99" : {"G" : 4243},
	"100" : {"L" : 3911},
	"101" : {"K" : 3256},
	"102" : {"K" : 3473},
	"103" : {"K" : 2755},
	"104" : {"K" : 3261},
	"105" : {"S" : 4253},
	"106" : {"V" : 4260},
	"107" : {"T" : 4262},
	"108" : {"V" : 4264},
	"109" : {"L" : 4266},
	"110" : {"D" : 4268},
	"111" : {"V" : 4271},
	"112" : {"G" : 4272},
	"113" : {"D" : 4274},
	"114" : {"A" : 4276},
	"115" : {"Y" : 4274},
	"116" : {"F" : 4154},
	"117" : {"S" : 4195},
	"118" : {"V" : 4276},
	"119" : {"P" : 4276},
	"120" : {"L" : 4278},
	"121" : {"D" : 4284},
	"122" : {"K" : 4277},
	"123" : {"D" : 4280},
	"124" : {"F" : 4286},
	"125" : {"R" : 4284},
	"126" : {"K" : 4290},
	"127" : {"Y" : 4293},
	"128" : {"T" : 4295},
	"129" : {"A" : 4296},
	"130" : {"F" : 4293},
	"131" : {"T" : 4296},
	"132" : {"I" : 4298},
	"133" : {"P" : 4299},
	"134" : {"S" : 4299},
	"135" : {"I" : 4295},
	"136" : {"N" : 4303},
	"137" : {"N" : 4303},
	"138" : {"E" : 4300},
	"139" : {"T" : 4302},
	"140" : {"P" : 4303},
	"141" : {"G" : 4284},
	"142" : {"V" : 4280},
	"143" : {"R" : 4255},
	"144" : {"Y" : 4306},
	"145" : {"Q" : 4305},
	"146" : {"Y" : 4307},
	"147" : {"N" : 4305},
	"148" : {"V" : 4307},
	"149" : {"L" : 4307},
	"150" : {"P" : 4305},
	"151" : {"Q" : 4301},
	"152" : {"G" : 4290},
	"153" : {"W" : 4283},
	"154" : {"K" : 4297},
	"155" : {"G" : 4306},
	"156" : {"S" : 4305},
	"157" : {"P" : 4303},
	"158" : {"A" : 4302},
	"159" : {"I" : 4302},
	"160" : {"F" : 4301},
	"161" : {"Q" : 4288},
	"162" : {"S" : 4289},
	"163" : {"S" : 4305},
	"164" : {"M" : 4304},
	"165" : {"T" : 4302},
	"166" : {"K" : 4154},
	"167" : {"I" : 4165},
	"168" : {"L" : 4290},
	"169" : {"E" : 4293},
	"170" : {"P" : 4287},
	"171" : {"F" : 4247},
	"172" : {"R" : 4175},
	"173" : {"K" : 4187},
	"174" : {"Q" : 3396},
	"175" : {"N" : 4198},
	"176" : {"P" : 4228},
	"177" : {"D" : 4225},
	"178" : {"I" : 4179},
	"179" : {"V" : 4198},
	"180" : {"I" : 4156},
	"181" : {"Y" : 4018},
	"182" : {"Q" : 4011},
	"183" : {"Y" : 3968},
	"184" : {"M" : 3956},
	"185" : {"D" : 3957}
}
